sparta/twitterapi/__init__.py
sparta/twitterapi/compliance/__init__.py
sparta/twitterapi/compliance/compliance.py
sparta/twitterapi/compliance/compliance_stream.py
sparta/twitterapi/models/compliance.py
sparta/twitterapi/models/tweet_response.py
sparta/twitterapi/models/twitter_v2_spec.py
sparta/twitterapi/py.typed
sparta/twitterapi/rate_limiter.py
sparta/twitterapi/trends/trends.py
sparta/twitterapi/trends/woeids.json
sparta/twitterapi/tweets/__init__.py
sparta/twitterapi/tweets/constants.py
sparta/twitterapi/tweets/filtered_stream.py
sparta/twitterapi/tweets/full_search.py
sparta/twitterapi/tweets/quote_tweets.py
sparta/twitterapi/tweets/recent_search.py
sparta/twitterapi/tweets/retweets.py
sparta/twitterapi/tweets/tweets.py
sparta/twitterapi/usage.py
sparta/twitterapi/users/follower.py
sparta/twitterapi/users/timeline.py
sparta/twitterapi/users/user.py
sparta_twitterapi-0.1.63.dist-info/LICENSE
sparta_twitterapi-0.1.63.dist-info/METADATA
sparta_twitterapi-0.1.63.dist-info/WHEEL
sparta_twitterapi-0.1.63.dist-info/RECORD
