Metadata-Version: 2.3
Name: sparta-twitterapi
Version: 0.1.63
Summary: 
Author: Andreas Neumeier
Author-email: andreas.neumeier@unibw.de
Requires-Python: >=3.10.12,<4.0.0
Classifier: Programming Language :: Python :: 3
Classifier: Programming Language :: Python :: 3.11
Classifier: Programming Language :: Python :: 3.12
Classifier: Programming Language :: Python :: 3.13
Requires-Dist: aiohttp (>=3.12.13,<4.0.0)
Requires-Dist: asyncio (>=3.4.3,<4.0.0)
Requires-Dist: pydantic (>=2.11.7,<3.0.0)
Requires-Dist: requests (>=2.32.4,<3.0.0)
